serializer_Konchik/__init__.py
serializer_Konchik/constants.py
serializer_Konchik/is_functions.py
serializer_Konchik/packer/__init__.py
serializer_Konchik/packer/packer.py
serializer_Konchik/packer/unpacker.py
serializer_Konchik/serializer/__init__.py
serializer_Konchik/serializer/base_serializer.py
serializer_Konchik/serializer/json_serializer.py
serializer_Konchik/serializer/serializer_factory.py
serializer_Konchik/serializer/xml_serializer.py
serializer_Konchik-0.1.8.dist-info/METADATA
serializer_Konchik-0.1.8.dist-info/WHEEL
serializer_Konchik-0.1.8.dist-info/top_level.txt
serializer_Konchik-0.1.8.dist-info/RECORD
