Metadata-Version: 2.1
Name: serializer-Konchik
Version: 0.1.8
Summary: JSON / XML serializer
Author: Denis Konchik
Author-email: denis.pptx@gmail.com
License: MIT
Classifier: Programming Language :: Python
Classifier: Operating System :: OS Independent
Requires-Python: >=3.11
Requires-Dist: regex
